{
  "coins": [
    {
      "coin": "BTC",
      "rates": {
        "binance": null,
        "bybit": null,
        "okx": 5.47576388172e-05,
        "bitget": 8e-06,
        "gate": null,
        "kucoin": null,
        "mexc": 7.7e-05,
        "hyperliquid": 4.15896e-05,
        "lighter": null
      },
      "average": 4.53368097043e-05,
      "sentiment": "neutral"
    },
    {
      "coin": "ETH",
      "rates": {
        "binance": null,
        "bybit": null,
        "okx": 5.8263591256e-06,
        "bitget": -2.3e-05,
        "gate": null,
        "kucoin": 7.7e-05,
        "mexc": -6e-06,
        "hyperliquid": -2.36992e-05,
        "lighter": null
      },
      "average": 6.025431825120002e-06,
      "sentiment": "neutral"
    },
    {
      "coin": "BNB",
      "rates": {
        "binance": null,
        "bybit": null,
        "okx": 6.82961219806e-05,
        "bitget": 5.6e-05,
        "gate": null,
        "kucoin": 5.8e-05,
        "mexc": 1e-05,
        "hyperliquid": 8.85664e-05,
        "lighter": null
      },
      "average": 5.617250439612e-05,
      "sentiment": "neutral"
    },
    {
      "coin": "SOL",
      "rates": {
        "binance": null,
        "bybit": null,
        "okx": 6.37552212551e-05,
        "bitget": 3.8e-05,
        "gate": null,
        "kucoin": 8.4e-05,
        "mexc": 4.1e-05,
        "hyperliquid": 8.08712e-05,
        "lighter": null
      },
      "average": 6.152528425102e-05,
      "sentiment": "neutral"
    },
    {
      "coin": "XRP",
      "rates": {
        "binance": null,
        "bybit": null,
        "okx": -2.84285794857e-05,
        "bitget": 3.5e-05,
        "gate": null,
        "kucoin": -2.2e-05,
        "mexc": 1.5e-05,
        "hyperliquid": 1.53848e-05,
        "lighter": null
      },
      "average": 2.991244102859999e-06,
      "sentiment": "neutral"
    },
    {
      "coin": "DOGE",
      "rates": {
        "binance": null,
        "bybit": null,
        "okx": 6.09148325392e-05,
        "bitget": 3.5e-05,
        "gate": null,
        "kucoin": 8.9e-05,
        "mexc": 1.6e-05,
        "hyperliquid": 3.70192e-05,
        "lighter": null
      },
      "average": 4.758680650784e-05,
      "sentiment": "neutral"
    },
    {
      "coin": "ADA",
      "rates": {
        "binance": null,
        "bybit": null,
        "okx": 6.72113755212e-05,
        "bitget": -0.000117,
        "gate": null,
        "kucoin": -9.5e-05,
        "mexc": -0.000121,
        "hyperliquid": -0.0001274912,
        "lighter": null
      },
      "average": -7.865596489576001e-05,
      "sentiment": "neutral"
    },
    {
      "coin": "AVAX",
      "rates": {
        "binance": null,
        "bybit": null,
        "okx": 0.0001,
        "bitget": 5e-05,
        "gate": null,
        "kucoin": 0.0001,
        "mexc": 8.7e-05,
        "hyperliquid": 0.0001,
        "lighter": null
      },
      "average": 8.74e-05,
      "sentiment": "neutral"
    },
    {
      "coin": "LINK",
      "rates": {
        "binance": null,
        "bybit": null,
        "okx": 8.15237912771e-05,
        "bitget": 1.7e-05,
        "gate": null,
        "kucoin": 4.6e-05,
        "mexc": 3.4e-05,
        "hyperliquid": 0.0001,
        "lighter": null
      },
      "average": 5.5704758255419994e-05,
      "sentiment": "neutral"
    },
    {
      "coin": "TRX",
      "rates": {
        "binance": null,
        "bybit": null,
        "okx": -3.93019512275e-05,
        "bitget": -7.7e-05,
        "gate": null,
        "kucoin": -0.000111,
        "mexc": -1.8e-05,
        "hyperliquid": 3.18136e-05,
        "lighter": null
      },
      "average": -4.26976702455e-05,
      "sentiment": "neutral"
    },
    {
      "coin": "TON",
      "rates": {
        "binance": null,
        "bybit": null,
        "okx": null,
        "bitget": null,
        "gate": null,
        "kucoin": null,
        "mexc": 0.0002,
        "hyperliquid": 0.0,
        "lighter": null
      },
      "average": 0.0001,
      "sentiment": "neutral"
    },
    {
      "coin": "SUI",
      "rates": {
        "binance": null,
        "bybit": null,
        "okx": 6.17587787184e-05,
        "bitget": 5.7e-05,
        "gate": null,
        "kucoin": 3.3e-05,
        "mexc": 4.1e-05,
        "hyperliquid": 0.0001,
        "lighter": null
      },
      "average": 5.855175574368e-05,
      "sentiment": "neutral"
    },
    {
      "coin": "XLM",
      "rates": {
        "binance": null,
        "bybit": null,
        "okx": -8.875803486e-06,
        "bitget": 4.4e-05,
        "gate": null,
        "kucoin": 1.1e-05,
        "mexc": -7.5e-05,
        "hyperliquid": -4.95632e-05,
        "lighter": null
      },
      "average": -1.5687800697199997e-05,
      "sentiment": "neutral"
    },
    {
      "coin": "HBAR",
      "rates": {
        "binance": null,
        "bybit": null,
        "okx": 3.04635127016e-05,
        "bitget": 0.0001,
        "gate": null,
        "kucoin": 0.0001,
        "mexc": 2.1e-05,
        "hyperliquid": 1.32048e-05,
        "lighter": null
      },
      "average": 5.293366254032001e-05,
      "sentiment": "neutral"
    },
    {
      "coin": "DOT",
      "rates": {
        "binance": null,
        "bybit": null,
        "okx": 4.00182818637e-05,
        "bitget": 0.0001,
        "gate": null,
        "kucoin": 0.0001,
        "mexc": 0.0001,
        "hyperliquid": -0.0004801552,
        "lighter": null
      },
      "average": -2.8027383627259992e-05,
      "sentiment": "neutral"
    },
    {
      "coin": "BCH",
      "rates": {
        "binance": null,
        "bybit": null,
        "okx": 3.58755308601e-05,
        "bitget": -9.3e-05,
        "gate": null,
        "kucoin": 1.9e-05,
        "mexc": -4.3e-05,
        "hyperliquid": -2.03752e-05,
        "lighter": null
      },
      "average": -2.029993382798e-05,
      "sentiment": "neutral"
    },
    {
      "coin": "LTC",
      "rates": {
        "binance": null,
        "bybit": null,
        "okx": 0.0001,
        "bitget": 0.0001,
        "gate": null,
        "kucoin": 0.0001,
        "mexc": 3.9e-05,
        "hyperliquid": 0.0001,
        "lighter": null
      },
      "average": 8.779999999999999e-05,
      "sentiment": "neutral"
    },
    {
      "coin": "UNI",
      "rates": {
        "binance": null,
        "bybit": null,
        "okx": 0.0001,
        "bitget": -2.7e-05,
        "gate": null,
        "kucoin": 2.5e-05,
        "mexc": 0.0001,
        "hyperliquid": 0.0001,
        "lighter": null
      },
      "average": 5.9600000000000005e-05,
      "sentiment": "neutral"
    },
    {
      "coin": "APT",
      "rates": {
        "binance": null,
        "bybit": null,
        "okx": 0.0001,
        "bitget": 0.0001,
        "gate": null,
        "kucoin": 0.0001,
        "mexc": 5.3e-05,
        "hyperliquid": 8.77312e-05,
        "lighter": null
      },
      "average": 8.814624000000001e-05,
      "sentiment": "neutral"
    },
    {
      "coin": "NEAR",
      "rates": {
        "binance": null,
        "bybit": null,
        "okx": 0.0001,
        "bitget": 0.0001,
        "gate": null,
        "kucoin": 5.5e-05,
        "mexc": 0.0001,
        "hyperliquid": 0.0001,
        "lighter": null
      },
      "average": 9.1e-05,
      "sentiment": "neutral"
    }
  ],
  "summary": {
    "bullish": 0,
    "bearish": 0,
    "neutral": 20
  },
  "exchanges": [
    {
      "id": "binance",
      "name": "Binance",
      "type": "cex"
    },
    {
      "id": "bybit",
      "name": "Bybit",
      "type": "cex"
    },
    {
      "id": "okx",
      "name": "OKX",
      "type": "cex"
    },
    {
      "id": "bitget",
      "name": "Bitget",
      "type": "cex"
    },
    {
      "id": "gate",
      "name": "Gate.io",
      "type": "cex"
    },
    {
      "id": "kucoin",
      "name": "KuCoin",
      "type": "cex"
    },
    {
      "id": "mexc",
      "name": "MEXC",
      "type": "cex"
    },
    {
      "id": "hyperliquid",
      "name": "Hyperliquid",
      "type": "dex"
    },
    {
      "id": "lighter",
      "name": "Lighter",
      "type": "dex"
    }
  ],
  "lastUpdated": "2026-06-29T07:32:41.070973Z"
}